deadsimplevenv/__init__.py
deadsimplevenv/config_default.yaml
deadsimplevenv/bin/__init__.py
deadsimplevenv/bin/dsv.py
deadsimplevenv/data/license/LICENSE_EMPTY
deadsimplevenv/data/license/LICENSE_GNU
deadsimplevenv/data/license/LICENSE_MIT
deadsimplevenv/data/static/.gitignore
deadsimplevenv/data/static/README.md
deadsimplevenv/data/static/pyproject.toml
deadsimplevenv/data/static/setup.cfg
deadsimplevenv/data/static/setup.py
deadsimplevenv-0.2.1.dist-info/LICENSE
deadsimplevenv-0.2.1.dist-info/METADATA
deadsimplevenv-0.2.1.dist-info/WHEEL
deadsimplevenv-0.2.1.dist-info/entry_points.txt
deadsimplevenv-0.2.1.dist-info/top_level.txt
deadsimplevenv-0.2.1.dist-info/RECORD
