Metadata-Version: 2.1
Name: deadsimplevenv
Version: 0.2.1
Summary: Dead simle wrapper for venv
Home-page: https://github.com/racoonx2p/deadsimplevenv
Author: racoonx2p
Author-email: racoonx2p@gmail.com
License: MIT
Keywords: venv
Platform: linux
Classifier: Development Status :: 3 - Alpha
Classifier: Intended Audience :: Developers
Classifier: License :: OSI Approved :: MIT License
Classifier: Programming Language :: Python
Classifier: Programming Language :: Python :: 3.6
Classifier: Programming Language :: Python :: 3.7
Classifier: Programming Language :: Python :: 3.8
Classifier: Topic :: Software Development :: Libraries :: Python Modules
Requires-Python: >=3.6
Requires-Dist: PyGithub
Requires-Dist: alive-progress
Requires-Dist: click
Requires-Dist: confuse
Requires-Dist: gitpython
Requires-Dist: jinja2
Requires-Dist: python-gitlab
Requires-Dist: questionary
Requires-Dist: wheel
